Metadata-Version: 2.1
Name: pydesy
Version: 0.0.5.1
Summary: Geodetic library
Home-page: https://github.com/ChevisOfficial/pydesy
Author: Maxim Shmakov
Author-email: shmakov.maxim2001@yandex.ru
License: UNKNOWN
Platform: UNKNOWN
